bme680/__init__.py
bme680/constants.py
bme680-1.1.1.dist-info/LICENSE.txt
bme680-1.1.1.dist-info/METADATA
bme680-1.1.1.dist-info/WHEEL
bme680-1.1.1.dist-info/top_level.txt
bme680-1.1.1.dist-info/RECORD
